stripedhyena/__init__.py
stripedhyena/cache.py
stripedhyena/engine.py
stripedhyena/generation.py
stripedhyena/layers.py
stripedhyena/model.py
stripedhyena/positional_embeddings.py
stripedhyena/sample.py
stripedhyena/tokenizer.py
stripedhyena/utils.py
stripedhyena-0.2.2.dist-info/LICENSE
stripedhyena-0.2.2.dist-info/METADATA
stripedhyena-0.2.2.dist-info/WHEEL
stripedhyena-0.2.2.dist-info/top_level.txt
stripedhyena-0.2.2.dist-info/RECORD
