Metadata-Version: 2.1
Name: stripedhyena
Version: 0.2.2
Summary: Model and inference code for beyond Transformer architectures
Home-page: http://github.com/togethercomputer/stripedhyena
Author: Michael Poli
License: Apache License
License-File: LICENSE
Requires-Dist: transformers
Requires-Dist: tokenizers
Requires-Dist: flash-attn >=2.0.0
